masterpiece/__init__.py
masterpiece/application.py
masterpiece/argmaestro.py
masterpiece/composite.py
masterpiece/format.py
masterpiece/jsonformat.py
masterpiece/log.py
masterpiece/masterpiece.py
masterpiece/masterpiecethread.py
masterpiece/mqtt.py
masterpiece/plugin.py
masterpiece/plugmaster.py
masterpiece/py.typed
masterpiece/supervisor.py
masterpiece/timeseries.py
masterpiece/treevisualizer.py
masterpiece/url.py
masterpiece-0.1.52.dist-info/licenses/LICENSE.rst
masterpiece-0.1.52.dist-info/METADATA
masterpiece-0.1.52.dist-info/WHEEL
masterpiece-0.1.52.dist-info/top_level.txt
masterpiece-0.1.52.dist-info/RECORD
