Metadata-Version: 2.4
Name: masterpiece
Version: 0.1.52
Summary: Masterpiece framework
Author-email: J Meskanen <juham.api@gmail.com>
Maintainer-email: "J. Meskanen" <juham.api@gmail.com>
License-Expression: MIT
Project-URL: Homepage, https://gitlab.com/juham/masterpiece
Project-URL: Bug Reports, https://gitlab.com/juham/masterpiece
Project-URL: Source, https://gitlab.com/juham/masterpiece
Project-URL: Say Thanks!, http://meskanen.com
Keywords: object-oriented,plugin,framework
Classifier: Development Status :: 3 - Alpha
Classifier: Intended Audience :: Developers
Classifier: Topic :: Software Development
Classifier: Programming Language :: Python :: 3.8
Requires-Python: >=3.8
License-File: LICENSE.rst
Requires-Dist: requests>=2.31
Requires-Dist: pytz>=2024.1
Requires-Dist: colorama>=0.3
Requires-Dist: typing-extensions>=4.5.0
Provides-Extra: dev
Requires-Dist: check-manifest; extra == "dev"
Requires-Dist: flake8; extra == "dev"
Requires-Dist: mypy; extra == "dev"
Requires-Dist: sphinx>=9; extra == "dev"
Requires-Dist: sphinx_bootstrap_theme; extra == "dev"
Requires-Dist: coverage>=7.6; extra == "dev"
Requires-Dist: pytest-cov; extra == "dev"
Requires-Dist: types-colorama; extra == "dev"
Dynamic: license-file
